pomodoro/__init__.py
pomodoro/audio.wav
pomodoro/config.py
pomodoro/constants.py
pomodoro/main.py
pomodoro_app_cli-1.3.0.dist-info/LICENSE
pomodoro_app_cli-1.3.0.dist-info/METADATA
pomodoro_app_cli-1.3.0.dist-info/WHEEL
pomodoro_app_cli-1.3.0.dist-info/entry_points.txt
pomodoro_app_cli-1.3.0.dist-info/RECORD
