Metadata-Version: 2.3
Name: pomodoro-app-cli
Version: 1.3.0
Summary: 🌟 Pomodoro CLI 🍅⏳ A simple and practical Pomodoro tool for your terminal! 📱💻 Organize your time efficiently with countdowns and sound alerts. Perfect for boosting productivity with focus and breaks! 🚀
License: MIT
Keywords: pomodoro,cli,terminal,linux,python,curses,timer
Author: Gustavo Soares
Author-email: gustavo.soares.cdc@gmail.com
Requires-Python: >=3.9,<4.0
Classifier: License :: OSI Approved :: MIT License
Classifier: Operating System :: OS Independent
Classifier: Programming Language :: Python :: 3
Classifier: Programming Language :: Python :: 3.9
Classifier: Programming Language :: Python :: 3.10
Classifier: Programming Language :: Python :: 3.11
Classifier: Programming Language :: Python :: 3.12
Classifier: Programming Language :: Python :: 3.13
Classifier: Topic :: Software Development :: Libraries :: Python Modules
Requires-Dist: inquirerpy (>=0.3.4,<0.4.0)
Requires-Dist: pyfiglet (>=1.0.2,<2.0.0)
Requires-Dist: rich (>=13.9.4,<14.0.0)
Project-URL: Homepage, https://github.com/GussSoares/pomodoro-cli
Project-URL: Repository, https://github.com/GussSoares/pomodoro-cli
